odoo/addons/hr_timesheet_unusual_days/README.rst
odoo/addons/hr_timesheet_unusual_days/__init__.py
odoo/addons/hr_timesheet_unusual_days/__manifest__.py
odoo/addons/hr_timesheet_unusual_days/i18n/hr_timesheet_unusual_days.pot
odoo/addons/hr_timesheet_unusual_days/i18n/it.po
odoo/addons/hr_timesheet_unusual_days/models/__init__.py
odoo/addons/hr_timesheet_unusual_days/models/account_analytic_line.py
odoo/addons/hr_timesheet_unusual_days/readme/CONTRIBUTORS.md
odoo/addons/hr_timesheet_unusual_days/readme/DESCRIPTION.md
odoo/addons/hr_timesheet_unusual_days/static/description/calendar.drawio.png
odoo/addons/hr_timesheet_unusual_days/static/description/icon.png
odoo/addons/hr_timesheet_unusual_days/static/description/index.html
odoo/addons/hr_timesheet_unusual_days/tests/__init__.py
odoo/addons/hr_timesheet_unusual_days/tests/test_account_analytic_line.py
odoo/addons/hr_timesheet_unusual_days/views/hr_timesheet_views.xml
odoo_addon_hr_timesheet_unusual_days-18.0.1.0.0.3.dist-info/METADATA
odoo_addon_hr_timesheet_unusual_days-18.0.1.0.0.3.dist-info/WHEEL
odoo_addon_hr_timesheet_unusual_days-18.0.1.0.0.3.dist-info/top_level.txt
odoo_addon_hr_timesheet_unusual_days-18.0.1.0.0.3.dist-info/RECORD
